video2frames/__init__.py
video2frames/cli.py
video2frames/extractor.py
video_frame_extractor_tool-0.2.0.dist-info/METADATA
video_frame_extractor_tool-0.2.0.dist-info/WHEEL
video_frame_extractor_tool-0.2.0.dist-info/entry_points.txt
video_frame_extractor_tool-0.2.0.dist-info/licenses/LICENSE
video_frame_extractor_tool-0.2.0.dist-info/RECORD
