Metadata-Version: 2.4
Name: video-frame-extractor-tool
Version: 0.2.0
Summary: Video Frame Extractor - Extract frames from videos using FFmpeg
Project-URL: Homepage, https://videotojpg.com
Project-URL: Documentation, https://github.com/Video-Frame-Extractor/Video-Frame-Extractor-Tool#readme
Project-URL: Repository, https://github.com/Video-Frame-Extractor/Video-Frame-Extractor-Tool
Project-URL: Issues, https://github.com/Video-Frame-Extractor/Video-Frame-Extractor-Tool/issues
Author-email: VideoToJPG <contact@videotojpg.com>
License: MIT
License-File: LICENSE
Keywords: extract frames from video,ffmpeg,frame-extraction,video frame extractor,video to image,video to jpg,video to png,video-converter,video-frame-extractor,video-processing
Classifier: Development Status :: 4 - Beta
Classifier: Environment :: Console
Classifier: Intended Audience :: Developers
Classifier: Intended Audience :: End Users/Desktop
Classifier: License :: OSI Approved :: MIT License
Classifier: Operating System :: OS Independent
Classifier: Programming Language :: Python :: 3
Classifier: Programming Language :: Python :: 3.7
Classifier: Programming Language :: Python :: 3.8
Classifier: Programming Language :: Python :: 3.9
Classifier: Programming Language :: Python :: 3.10
Classifier: Programming Language :: Python :: 3.11
Classifier: Programming Language :: Python :: 3.12
Classifier: Topic :: Multimedia :: Video
Classifier: Topic :: Multimedia :: Video :: Conversion
Classifier: Topic :: Utilities
Requires-Python: >=3.7
